gradle.properties
hexdoc_dthexcasting/__gradle_version__.py
hexdoc_dthexcasting/__init__.py
hexdoc_dthexcasting/__version__.py
hexdoc_dthexcasting/_hooks.py
hexdoc_dthexcasting/py.typed
hexdoc_dthexcasting/_export/.gitignore
hexdoc_dthexcasting/_export/__init__.py
hexdoc_dthexcasting/_export/generated/__init__.py
hexdoc_dthexcasting/_export/generated/dthexcasting.hexdoc.json
hexdoc_dthexcasting/_export/generated/dthexcasting.patterns.hexdoc.json
hexdoc_dthexcasting/_export/generated/assets/dthexcasting/lang/en_us.json
hexdoc_dthexcasting/_export/generated/assets/dthexcasting/lang/zh_cn.json
hexdoc_dthexcasting/_export/generated/assets/dthexcasting/models/item/edified_amethyst_branch.json
hexdoc_dthexcasting/_export/generated/assets/dthexcasting/models/item/edified_aventurine_branch.json
hexdoc_dthexcasting/_export/generated/assets/dthexcasting/models/item/edified_citrine_branch.json
hexdoc_dthexcasting/_export/generated/assets/dynamictrees/lang/en_us.json
hexdoc_dthexcasting/_export/generated/assets/dynamictrees/textures/item/dark_oak_seed.png
hexdoc_dthexcasting/_export/generated/assets/dynamictrees/textures/item/oak_seed.png
hexdoc_dthexcasting/_export/generated/assets/hexcasting/lang/en_us.flatten.json5
hexdoc_dthexcasting/_export/generated/assets/hexcasting/patchouli_books/thehexbook/en_us/entries/patterns/tree_patterns.json
hexdoc_dthexcasting/_export/generated/assets/hexcasting/patchouli_books/thehexbook/en_us/entries/patterns/spells/tree_spells.json
hexdoc_dthexcasting/_export/generated/assets/hexcasting/textures/block/edified_log_top.png
hexdoc_dthexcasting/_export/generated/assets/hexcasting/textures/block/deco/edified_log_amethyst.png
hexdoc_dthexcasting/_export/generated/assets/hexcasting/textures/block/deco/edified_log_aventurine.png
hexdoc_dthexcasting/_export/generated/assets/hexcasting/textures/block/deco/edified_log_citrine.png
hexdoc_dthexcasting/_export/generated/data/hexcasting/tags/action/per_world_pattern.json
hexdoc_dthexcasting-1.0.2.1.0.dist-info/METADATA
hexdoc_dthexcasting-1.0.2.1.0.dist-info/WHEEL
hexdoc_dthexcasting-1.0.2.1.0.dist-info/entry_points.txt
hexdoc_dthexcasting-1.0.2.1.0.dist-info/licenses/LICENSE
hexdoc_dthexcasting-1.0.2.1.0.dist-info/RECORD
